setup.py
modular_gui/__init__.py
modular_gui/main.py
modular_gui.egg-info/PKG-INFO
modular_gui.egg-info/SOURCES.txt
modular_gui.egg-info/dependency_links.txt
modular_gui.egg-info/entry_points.txt
modular_gui.egg-info/requires.txt
modular_gui.egg-info/top_level.txt
modular_gui/ui/__init__.py
modular_gui/ui/menubar/__init__.py
modular_gui/ui/menubar/file_menu.py