Metadata-Version: 1.0
Name: modular-gui
Version: 0.0.1
Summary: Modular GUI using PySide
Home-page: https://github.com/davidmartinezanim/Modular_GUI
Author: David Martinez
Author-email: david.martinez.anim@gmail.com
License: UNKNOWN
Platform: UNKNOWN
